tachy/__init__.py
tachy/config.py
tachy/datamodule.py
tachy/module.py
tachy/predictor.py
tachy/schedulers.py
tachy/trainer.py
tachy/utils.py
tachy-0.1.0a1.dist-info/METADATA
tachy-0.1.0a1.dist-info/WHEEL
tachy-0.1.0a1.dist-info/entry_points.txt
tachy-0.1.0a1.dist-info/RECORD
